imix/__init__.py
imix/version.py
imix/data/__init__.py
imix/data/builder.py
imix/data/infocomp/__init__.py
imix/data/infocomp/base_infocpler.py
imix/data/infocomp/clevr_infocpler.py
imix/data/infocomp/gqa_infocpler.py
imix/data/infocomp/hatefulememes_infocpler.py
imix/data/infocomp/lxmertpretrain_infocpler.py
imix/data/infocomp/ocrvqa_infocpler.py
imix/data/infocomp/refclef_infocpler.py
imix/data/infocomp/refcoco2_infocpler.py
imix/data/infocomp/refcoco_infocpler.py
imix/data/infocomp/refcocog_infocpler.py
imix/data/infocomp/refcocop_infocpler.py
imix/data/infocomp/referit_infocpler.py
imix/data/infocomp/stvqa_infocpler.py
imix/data/infocomp/textvqa_infocpler.py
imix/data/infocomp/vcr_infocpler.py
imix/data/infocomp/visual_dialog_infocpler.py
imix/data/infocomp/visualentailment_infocpler.py
imix/data/infocomp/vizwiz_infocpler.py
imix/data/infocomp/vqa_infocpler.py
imix/data/loaders/__init__.py
imix/data/loaders/_image_features_reader.py
imix/data/loaders/base_loader.py
imix/data/loaders/clevr_loader.py
imix/data/loaders/gqa_loader.py
imix/data/loaders/hatefulmemes_loader.py
imix/data/loaders/ocrvqa_loader.py
imix/data/loaders/refclef_loader.py
imix/data/loaders/refcoco_loader.py
imix/data/loaders/refcocog_loader.py
imix/data/loaders/refcocop_loader.py
imix/data/loaders/referit_loader.py
imix/data/loaders/stvqa_loader.py
imix/data/loaders/textvqa_loader.py
imix/data/loaders/vcr_loader.py
imix/data/loaders/visual_dialog_dataset.py
imix/data/loaders/visualentailment_loader.py
imix/data/loaders/vizwiz_loader.py
imix/data/loaders/vqa_loader.py
imix/data/loaders/vqa_loader_uniter.py
imix/data/reader/__init__.py
imix/data/reader/annotation_reader.py
imix/data/reader/base_reader.py
imix/data/reader/clevr_reader.py
imix/data/reader/feature_base_data.py
imix/data/reader/gqa_reader.py
imix/data/reader/hatefulmemes_reader.py
imix/data/reader/lxmertpretrain_reader.py
imix/data/reader/ocrvqa_reader.py
imix/data/reader/refclef_reader.py
imix/data/reader/refcoco2_reader.py
iMIX-0.1.0.dist-info/LICENSE
iMIX-0.1.0.dist-info/METADATA
iMIX-0.1.0.dist-info/WHEEL
iMIX-0.1.0.dist-info/top_level.txt
iMIX-0.1.0.dist-info/RECORD
