Metadata-Version: 2.1
Name: iMIX
Version: 0.1.0
Summary: multimodal deep learning framework
Home-page: https://github.com/inspur-hsslab/iMIX
Author: Inspur iMIX
Author-email: hsslab.inspur@gmail.com
License: Apache License 2.0
Keywords: multimodal,computer vision,object detection,multi-task vision
Platform: UNKNOWN
Classifier: Development Status :: 5 - Production/Stable
Classifier: License :: OSI Approved :: Apache Software License
Classifier: Operating System :: OS Independent
Classifier: Programming Language :: Python :: 3
Classifier: Programming Language :: Python :: 3.6
Classifier: Programming Language :: Python :: 3.7
Classifier: Programming Language :: Python :: 3.8
Requires-Dist: allennlp (==1.2.2)
Requires-Dist: anytree (==2.8.0)
Requires-Dist: boto3 (==1.16.46)
Requires-Dist: botocore (==1.19.46)
Requires-Dist: Cython (==0.29.21)
Requires-Dist: cytoolz (==0.9.0.1)
Requires-Dist: dict (==2020.12.3)
Requires-Dist: docformatter (==1.3.1)
Requires-Dist: easydict (==1.9)
Requires-Dist: fasttext (==0.9.1)
Requires-Dist: flask (>=1.12)
Requires-Dist: flask-cors (>=3.0.10)
Requires-Dist: h5py (==3.1.0)
Requires-Dist: json-lines (==0.5.0)
Requires-Dist: jsonlines (==1.2.0)
Requires-Dist: lmdb (==0.98)
Requires-Dist: lz4 (==3.1.3)
Requires-Dist: matplotlib (==3.3.3)
Requires-Dist: mmcv-full (==1.2.4)
Requires-Dist: msgpack (==0.5.6)
Requires-Dist: nltk (==3.4.5)
Requires-Dist: numpy (==1.19.4)
Requires-Dist: omegaconf (==2.0.1rc4)
Requires-Dist: overrides (==3.1.0)
Requires-Dist: Pillow (==8.0.1)
Requires-Dist: portalocker (==2.0.0)
Requires-Dist: pre-commit (==2.9.3)
Requires-Dist: py (==1.10.0)
Requires-Dist: pytorch-pretrained-bert (==0.6.2)
Requires-Dist: recommonmark
Requires-Dist: regex (==2018.1.10)
Requires-Dist: requests (==2.23.0)
Requires-Dist: scipy (==1.5.4)
Requires-Dist: six (==1.15.0)
Requires-Dist: sphinx
Requires-Dist: sphinx-markdown-tables
Requires-Dist: sphinx-rtd-theme
Requires-Dist: tabulate (==0.8.7)
Requires-Dist: tensorpack (==0.9.4)
Requires-Dist: termcolor (==1.1.0)
Requires-Dist: terminaltables (==3.1.0)
Requires-Dist: toolz (==0.11.1)
Requires-Dist: torch (==1.7.1)
Requires-Dist: torchtext (==0.5.0)
Requires-Dist: torchvision (==0.8.2)
Requires-Dist: tqdm (==4.55.0)
Requires-Dist: transformers (==3.4.0)
Requires-Dist: values (==2020.12.3)
Requires-Dist: yacs (>=0.1.8)
Requires-Dist: yapf (==0.30.0)
